imagebot/__init__.py
imagebot/__version__.py
imagebot/_base_matcher.py
imagebot/_compare.py
imagebot/_convertor.py
imagebot/_feature_matcher.py
imagebot/_generic_matcher.py
imagebot/_results.py
imagebot/_template_matcher.py
image_bot_cv2-0.1.5.dist-info/LICENSE
image_bot_cv2-0.1.5.dist-info/METADATA
image_bot_cv2-0.1.5.dist-info/WHEEL
image_bot_cv2-0.1.5.dist-info/top_level.txt
image_bot_cv2-0.1.5.dist-info/RECORD
