Metadata-Version: 2.1
Name: image-bot-cv2
Version: 0.1.5
Summary: Image matching/comparison based on open-cv
Home-page: https://github.com/jnhyperion/ImageBot
Author: Johnny Huang
Author-email: jnhyperion@gmail.com
License: UNKNOWN
Keywords: opencv image matching comparison
Platform: UNKNOWN
Classifier: Programming Language :: Python :: 3
Classifier: Operating System :: OS Independent
Requires-Python: >=3.8
License-File: LICENSE
Requires-Dist: numpy (<=1.22.4,>=1.21.0)
Requires-Dist: opencv-python (<=4.6.0.66,>=4.5.3.56)
